jupyterlab_magic_wand/__init__.py
jupyterlab_magic_wand/_version.py
jupyterlab_magic_wand/extension.py
jupyterlab_magic_wand/rest_handlers.py
jupyterlab_magic_wand/utils.py
jupyterlab_magic_wand/agents/base.py
jupyterlab_magic_wand/agents/magic_agent.py
jupyterlab_magic_wand/agents/tools/__init__.py
jupyterlab_magic_wand/agents/tools/insert_cell_below.py
jupyterlab_magic_wand/agents/tools/show_diff.py
jupyterlab_magic_wand/agents/tools/update_cell_source.py
jupyterlab_magic_wand/events/jai-error.yml
jupyterlab_magic_wand-0.6.0.data/data/etc/jupyter/jupyter_server_config.d/jupyterlab_magic_wand.json
jupyterlab_magic_wand-0.6.0.data/data/share/jupyter/labextensions/jupyterlab_magic_wand/package.json
jupyterlab_magic_wand-0.6.0.data/data/share/jupyter/labextensions/jupyterlab_magic_wand/schemas/jupyterlab_magic_wand/button.json
jupyterlab_magic_wand-0.6.0.data/data/share/jupyter/labextensions/jupyterlab_magic_wand/schemas/jupyterlab_magic_wand/package.json.orig
jupyterlab_magic_wand-0.6.0.data/data/share/jupyter/labextensions/jupyterlab_magic_wand/static/108.6de00b387836b7a0efe2.js
jupyterlab_magic_wand-0.6.0.data/data/share/jupyter/labextensions/jupyterlab_magic_wand/static/299.270f3459b0d61e8c29f2.js
jupyterlab_magic_wand-0.6.0.data/data/share/jupyter/labextensions/jupyterlab_magic_wand/static/339.fb5f112f4526e14b747c.js
jupyterlab_magic_wand-0.6.0.data/data/share/jupyter/labextensions/jupyterlab_magic_wand/static/680.270f3459b0d61e8c29f2.js
jupyterlab_magic_wand-0.6.0.data/data/share/jupyter/labextensions/jupyterlab_magic_wand/static/727.6de00b387836b7a0efe2.js
jupyterlab_magic_wand-0.6.0.data/data/share/jupyter/labextensions/jupyterlab_magic_wand/static/728.b2230e681bc3e4badb65.js
jupyterlab_magic_wand-0.6.0.data/data/share/jupyter/labextensions/jupyterlab_magic_wand/static/remoteEntry.4f4b98c1ac460ec9122d.js
jupyterlab_magic_wand-0.6.0.data/data/share/jupyter/labextensions/jupyterlab_magic_wand/static/style.js
jupyterlab_magic_wand-0.6.0.dist-info/METADATA
jupyterlab_magic_wand-0.6.0.dist-info/WHEEL
jupyterlab_magic_wand-0.6.0.dist-info/entry_points.txt
jupyterlab_magic_wand-0.6.0.dist-info/licenses/LICENSE
jupyterlab_magic_wand-0.6.0.dist-info/RECORD
