Metadata-Version: 2.4
Name: jupyterlab_magic_wand
Version: 0.6.0
Summary: An in-cell AI assistant for JupyterLab notebooks
Project-URL: Homepage, https://github.com/jupyter-ai-contrib/jupyterlab-magic-wand
Project-URL: Bug Tracker, https://github.com/jupyter-ai-contrib/jupyterlab-magic-wand/issues
Project-URL: Repository, https://github.com/jupyter-ai-contrib/jupyterlab-magic-wand.git
Author-email: Zach Sailer <zachsailer@gmail.com>
License: BSD 3-Clause License
License-File: LICENSE
Keywords: jupyter,jupyterlab,jupyterlab-extension
Classifier: Framework :: Jupyter
Classifier: Framework :: Jupyter :: JupyterLab
Classifier: Framework :: Jupyter :: JupyterLab :: 4
Classifier: Framework :: Jupyter :: JupyterLab :: Extensions
Classifier: Framework :: Jupyter :: JupyterLab :: Extensions :: Prebuilt
Classifier: License :: OSI Approved :: BSD License
Classifier: Programming Language :: Python
Classifier: Programming Language :: Python :: 3
Classifier: Programming Language :: Python :: 3.8
Classifier: Programming Language :: Python :: 3.9
Classifier: Programming Language :: Python :: 3.10
Classifier: Programming Language :: Python :: 3.11
Classifier: Programming Language :: Python :: 3.12
Requires-Python: >=3.8
Requires-Dist: cachetools
Requires-Dist: importlib-metadata
Requires-Dist: jupyter-server<3,>=2.0.1
Requires-Dist: jupyterlab-cell-diff>=0.4.2
Requires-Dist: jupyterlab-cell-input-footer>=0.3.1
Requires-Dist: jupyterlab-eventlistener>=0.4.0
Requires-Dist: jupyterlab>=4.0.0
Requires-Dist: langchain
Requires-Dist: langgraph
